poetry_plugin_petrify/__init__.py
poetry_plugin_petrify/app.py
poetry_plugin_petrify-2.0.0.dist-info/LICENSE
poetry_plugin_petrify-2.0.0.dist-info/METADATA
poetry_plugin_petrify-2.0.0.dist-info/WHEEL
poetry_plugin_petrify-2.0.0.dist-info/entry_points.txt
poetry_plugin_petrify-2.0.0.dist-info/RECORD
