Metadata-Version: 2.1
Name: poetry-plugin-petrify
Version: 2.0.0
Summary: Poetry plugin to petrify a wheel's dependencies per lock file
Home-page: https://github.com/KPLauritzen/poetry-plugin-petrify
License: Apache-2.0
Author: Kasper Primdal Lauritzen
Author-email: git@kplauritzen.dk
Requires-Python: >=3.10,<3.13
Classifier: License :: OSI Approved :: Apache Software License
Classifier: Programming Language :: Python :: 3
Classifier: Programming Language :: Python :: 3.10
Classifier: Programming Language :: Python :: 3.11
Classifier: Programming Language :: Python :: 3.12
Requires-Dist: poetry (>=1.8.4,<2.0.0)
Requires-Dist: poetry-core (>=1.9.0,<2.0.0)
